[
  {
    "name": "default",
    "widgets": [
      {
        "name": "weeklyseries",
        "sizeX": 10,
        "sizeY": 10,
        "content": {
          "options": {},
          "queryString": "reportDate: [2009-03-06 TO 2010-06-04]",
          "filters": [
            {
              "id": 0,
              "row": 0,
              "col": 0,
              "type": "date-range",
              "from": "2009-03-07T00:00:00.000Z",
              "to": "2010-06-05T00:00:00.000Z",
              "queryString": "reportDate: [2009-03-06 TO 2010-06-04]"
            }
          ],
          "series": [],
          "interval": "week",
          "down": false,
          "timeseries": {
            "xmin": 1235952000000,
            "xmax": 1275696000000,
            "ymin": 1,
            "ymax": 210,
            "legendHeight": 25,
            "height": 300,
            "width": 553,
            "ymargin": 20,
            "xmargin": 36.5,
            "palette": [
              "#1f77b4"
            ]
          },
          "visualization": {
            "name": "line"
          },
          "pivot": {
            "cols": []
          },
          "name": "weeklyseries"
        },
        "row": 0,
        "col": 0
      },
      {
        "name": "sexbarchart",
        "sizeX": 10,
        "sizeY": 10,
        "content": {
          "filters": [
            {
              "id": 0,
              "row": 0,
              "col": 0,
              "type": "date-range",
              "from": "2014-03-07T00:00:00.000Z",
              "to": "2014-06-05T00:00:00.000Z",
              "queryString": "reportDate: [2014-03-07 TO 2014-06-05]"
            }
          ],
          "queryString": "reportDate: [2014-03-07 TO 2014-06-05]",
          "visualization": {
            "name": "bar"
          },
          "pivot": {
            "rows": [],
            "cols": [
              "sex"
            ]
          },
          "options": {},
          "aggData": [
            {
              "col": "sex",
              "colName": "female",
              "key": "female",
              "values": [
                {
                  "col": "sex",
                  "colName": "female",
                  "key": "female",
                  "value": 3,
                  "series": 0
                }
              ]
            },
            {
              "col": "sex",
              "colName": "male",
              "key": "male",
              "values": [
                {
                  "col": "sex",
                  "colName": "male",
                  "key": "male",
                  "value": 2,
                  "series": 1
                }
              ]
            },
            {
              "col": "sex",
              "colName": "missing",
              "key": "missing_sex",
              "values": [
                {
                  "col": "sex",
                  "colName": "missing",
                  "key": "missing_sex",
                  "value": 7,
                  "series": 2
                }
              ]
            }
          ],
          "crosstabData": [],
          "strings": {
            "date": "Date",
            "district": "District",
            "sex": "Sex",
            "age": "Age",
            "symptoms": "Symptoms",
            "edit": "Edit"
          },
          "tableParams": {
            "data": [
              {
                "_index": "outpatient",
                "_type": "visit",
                "_id": "t8Z7O854RcSu6m-Ddu-yjQ",
                "_version": 1,
                "_score": null,
                "_source": {
                  "patient": {
                    "age": null,
                    "weight": null
                  },
                  "symptoms": [
                    "Fever Test"
                  ],
                  "diagnoses": [],
                  "reportDate": "2014-05-01T04:00:00.000Z",
                  "medicalFacility": {
                    "district": "Alphaville"
                  }
                },
                "sort": [
                  1398916800000
                ]
              },
              {
                "_index": "outpatient",
                "_type": "visit",
                "_id": "iIl0wOrmQJGih7OgpEfSpg",
                "_version": 9,
                "_score": null,
                "_source": {
                  "symptoms": [],
                  "diagnoses": [],
                  "reportDate": "2014-05-01T04:00:00.000Z",
                  "medicalFacility": {
                    "district": "Alphaville"
                  },
                  "patient": {
                    "sex": "male",
                    "age": 70,
                    "weight": 60
                  }
                },
                "sort": [
                  1398916800000
                ]
              },
              {
                "_index": "outpatient",
                "_type": "visit",
                "_id": "A3fLo56gQS-soaY5RLZ3-g",
                "_version": 8,
                "_score": null,
                "_source": {
                  "reportDate": "2014-04-22T16:40:09.655Z",
                  "medicalFacility": {
                    "district": "District 3"
                  },
                  "patient": {
                    "sex": "female",
                    "age": 80
                  },
                  "symptoms": [],
                  "diagnoses": []
                },
                "sort": [
                  1398184809655
                ]
              },
              {
                "_index": "outpatient",
                "_type": "visit",
                "_id": "iU_km4HDTdSPZZ47zAXO2w",
                "_version": 2,
                "_score": null,
                "_source": {
                  "reportDate": "2014-04-16T04:00:00.000Z",
                  "patient": {
                    "sex": "female"
                  },
                  "symptoms": [],
                  "diagnoses": []
                },
                "sort": [
                  1397620800000
                ]
              },
              {
                "_index": "outpatient",
                "_type": "visit",
                "_id": "TnvBsQijTyWyKsXz78qNVg",
                "_version": 3,
                "_score": null,
                "_source": {
                  "reportDate": "2014-04-16",
                  "patient": {
                    "age": 20
                  },
                  "medicalFacility": {
                    "district": "District 2"
                  },
                  "symptoms": [],
                  "diagnoses": []
                },
                "sort": [
                  1397606400000
                ]
              },
              {
                "_index": "outpatient",
                "_type": "visit",
                "_id": "ymktzT9fTVubpRLvgLjSwA",
                "_version": 1,
                "_score": null,
                "_source": {
                  "reportDate": "2014-04-16",
                  "patient": {
                    "age": 31,
                    "sex": "female"
                  },
                  "medicalFacility": {
                    "district": "District 2"
                  }
                },
                "sort": [
                  1397606400000
                ]
              },
              {
                "_index": "outpatient",
                "_type": "visit",
                "_id": "9iWwRrtdQ-aSL30pm54K8A",
                "_version": 1,
                "_score": null,
                "_source": {
                  "reportDate": "2014-04-02T21:18:49.569Z",
                  "medicalFacility": {
                    "district": "District 1"
                  },
                  "symptoms": [
                    "abdominal pain"
                  ]
                },
                "sort": [
                  1396473529569
                ]
              },
              {
                "_index": "outpatient",
                "_type": "visit",
                "_id": "pPGTZR-kRYOyqc7lF5BXwQ",
                "_version": 1,
                "_score": null,
                "_source": {
                  "reportDate": "2014-04-02T04:00:00.000Z",
                  "medicalFacility": {
                    "district": "District 1"
                  },
                  "patient": {
                    "age": 3
                  }
                },
                "sort": [
                  1396411200000
                ]
              },
              {
                "_index": "outpatient",
                "_type": "visit",
                "_id": "an7LkiA_RNe9wFQRJzyJkA",
                "_version": 1,
                "_score": null,
                "_source": {
                  "reportDate": "2014-04-01T21:18:49.569Z",
                  "medicalFacility": {
                    "district": "District 1"
                  },
                  "symptoms": [
                    "abdominal pain",
                    "cold"
                  ]
                },
                "sort": [
                  1396387129569
                ]
              },
              {
                "_index": "outpatient",
                "_type": "visit",
                "_id": "eJ-Qh1T5SfqcBXPRVpXbVQ",
                "_version": 1,
                "_score": null,
                "_source": {
                  "symptoms": [
                    "abdominal pain",
                    "cough"
                  ],
                  "reportDate": "2014-03-31",
                  "medicalFacility": {
                    "district": "District 3"
                  }
                },
                "sort": [
                  1396224000000
                ]
              }
            ]
          },
          "name": "sexbarchart"
        },
        "row": 0,
        "col": 11
      }
    ]
  }
]
